disamby/__init__.py
disamby/cli.py
disamby/core.py
disamby/preprocessors.py
disamby-0.2.4.dist-info/DESCRIPTION.rst
disamby-0.2.4.dist-info/METADATA
disamby-0.2.4.dist-info/RECORD
disamby-0.2.4.dist-info/WHEEL
disamby-0.2.4.dist-info/entry_points.txt
disamby-0.2.4.dist-info/metadata.json
disamby-0.2.4.dist-info/top_level.txt
