Metadata-Version: 2.0
Name: disamby
Version: 0.2.4
Summary: Python package to carry out entity disambiguation based on string matching
Home-page: https://github.com/verginer/disamby
Author: Luca Verginer
Author-email: luca@verginer.eu
License: MIT license
Keywords: disamby,disambiguation
Platform: UNKNOWN
Classifier: Development Status :: 2 - Pre-Alpha
Classifier: Intended Audience :: Developers
Classifier: Intended Audience :: Science/Research
Classifier: License :: OSI Approved :: MIT License
Classifier: Natural Language :: English
Classifier: Programming Language :: Python :: 3
Classifier: Programming Language :: Python :: 3.5
Classifier: Programming Language :: Python :: 3.6
Requires-Dist: Click (>=6.0)
Requires-Dist: networkx
Requires-Dist: tqdm
